verilog_crypt/__init__.py
verilog_crypt/crypt_algo.cpython-38-x86_64-linux-gnu.so
verilog_crypt/crypt_interface.cpython-38-x86_64-linux-gnu.so
verilog_crypt/crypt_local.cpython-38-x86_64-linux-gnu.so
verilog_crypt/crypt_local_def_rules.txt
verilog_crypt/crypt_module_def_rules.txt
verilog_crypt/module.cpython-38-x86_64-linux-gnu.so
verilog_crypt-0.0.2.dist-info/METADATA
verilog_crypt-0.0.2.dist-info/WHEEL
verilog_crypt-0.0.2.dist-info/top_level.txt
verilog_crypt-0.0.2.dist-info/RECORD
